stark/__init__.py
stark/__main__.py
stark/_version.py
stark/cli.py
stark/stark.py
stark/utils.py
stark/__pycache__/__init__.cpython-310.pyc
stark/__pycache__/__init__.pypy38.pyc
stark/__pycache__/stark.cpython-310.pyc
stark/__pycache__/stark.pypy38.pyc
stark/__pycache__/utils.cpython-310.pyc
stark/__pycache__/utils.pypy38.pyc
stark/data/__init__.py
stark/data/document.py
stark/data/summary.py
stark/data/__pycache__/__init__.cpython-310.pyc
stark/data/__pycache__/__init__.pypy38.pyc
stark/data/__pycache__/document.cpython-310.pyc
stark/data/__pycache__/document.pypy38.pyc
stark/data/__pycache__/summary.cpython-310.pyc
stark/data/__pycache__/summary.pypy38.pyc
stark/data/processing/__init__.py
stark/data/processing/greedy_tree.py
stark/data/processing/query_tree.py
stark/data/processing/tree.py
stark/data/processing/__pycache__/__init__.cpython-310.pyc
stark/data/processing/__pycache__/__init__.pypy38.pyc
stark/data/processing/__pycache__/greedy_tree.cpython-310.pyc
stark/data/processing/__pycache__/greedy_tree.pypy38.pyc
stark/data/processing/__pycache__/query_tree.cpython-310.pyc
stark/data/processing/__pycache__/query_tree.pypy38.pyc
stark/data/processing/__pycache__/tree.cpython-310.pyc
stark/data/processing/__pycache__/tree.pypy38.pyc
stark/data/representation/__init__.py
stark/data/representation/empty_namespace.py
stark/data/representation/greedy_tree.py
stark/data/representation/node.py
stark/data/representation/query_tree.py
stark/data/representation/tree.py
stark/data/representation/__pycache__/__init__.cpython-310.pyc
stark/data/representation/__pycache__/__init__.pypy38.pyc
stark/data/representation/__pycache__/empty_namespace.cpython-310.pyc
stark/data/representation/__pycache__/greedy_tree.cpython-310.pyc
stark/data/representation/__pycache__/greedy_tree.pypy38.pyc
stark/data/representation/__pycache__/node.cpython-310.pyc
stark/data/representation/__pycache__/node.pypy38.pyc
stark/data/representation/__pycache__/query_tree.cpython-310.pyc
stark_trees-3.1.0.dist-info/licenses/LICENSE.txt
stark_trees-3.1.0.dist-info/METADATA
stark_trees-3.1.0.dist-info/WHEEL
stark_trees-3.1.0.dist-info/entry_points.txt
stark_trees-3.1.0.dist-info/top_level.txt
stark_trees-3.1.0.dist-info/RECORD
