Metadata-Version: 2.4
Name: stark-trees
Version: 3.1.0
Summary: Parser for dependency trees
Home-page: https://github.com/clarinsi/STARK.git
Author: CLARIN.SI
Author-email: info@clarin.si
License: Apache 2.0
Keywords: universal-dependencies dependency-parsing dependency-trees subtree-extraction treebank syntactic-analysis corpus-linguistics computational-linguistics text-analysis syntax extraction comparison natural-language-processing nlp natural-language-understanding clarinsi
Classifier: Development Status :: 4 - Beta
Classifier: Intended Audience :: Developers
Classifier: Intended Audience :: Education
Classifier: Intended Audience :: Science/Research
Classifier: Intended Audience :: Information Technology
Classifier: Topic :: Scientific/Engineering
Classifier: Topic :: Scientific/Engineering :: Information Analysis
Classifier: Topic :: Text Processing
Classifier: Topic :: Text Processing :: Filters
Classifier: Topic :: Text Processing :: Linguistic
Classifier: Topic :: Software Development
Classifier: Topic :: Software Development :: Libraries
Classifier: Programming Language :: Python :: 3.6
Classifier: Programming Language :: Python :: 3.7
Classifier: Programming Language :: Python :: 3.8
Classifier: Programming Language :: Python :: 3.9
Classifier: Programming Language :: Python :: 3.10
Requires-Python: >=3.6
License-File: LICENSE.txt
Requires-Dist: pyconll>=3.1.0
Requires-Dist: networkx>=3.3
Requires-Dist: tqdm>=4.66.4
Dynamic: author
Dynamic: author-email
Dynamic: classifier
Dynamic: description
Dynamic: description-content-type
Dynamic: home-page
Dynamic: keywords
Dynamic: license
Dynamic: license-file
Dynamic: requires-dist
Dynamic: requires-python
Dynamic: summary
